codefast/__init__.py
codefast/argparser.py
codefast/axe.py
codefast/cn.py
codefast/concurrency.py
codefast/constants.py
codefast/core.py
codefast/ds.py
codefast/exception.py
codefast/logger.py
codefast/math.py
codefast/reader.py
codefast/text.py
codefast/tmp.py
codefast/utils.py
codefast/algorithm/__init__.py
codefast/algorithm/str.py
codefast/asyncio/__init__.py
codefast/asyncio/rabbitmq.py
codefast/axe/__init__.py
codefast/axe/axe.py
codefast/base/__init__.py
codefast/base/format_print.py
codefast/betterargs/__init__.py
codefast/betterargs/abstractclient.py
codefast/concurrent/__init__.py
codefast/concurrent/fastapi_demo.py
codefast/concurrent/scheduler.py
codefast/decorators/__init__.py
codefast/decorators/log.py
codefast/decorators/retry.py
codefast/experimental/__init__.py
codefast/experimental/nsq.py
codefast/fio/__init__.py
codefast/fio/ffpb.py
codefast/frameworks/__init__.py
codefast/functools/__init__.py
codefast/functools/random.py
codefast/functools/subroutine.py
codefast/io/__init__.py
codefast/io/_json.py
codefast/io/dblite.py
codefast/io/fdb.py
codefast/io/file.py
codefast/io/osdb.py
codefast/io/sqlite.py
codefast/network/__init__.py
codefast/network/curl.py
codefast/network/factory.py
codefast/network/richdownloader.py
codefast/network/tools.py
codefast/os/__init__.py
codefast/patterns/__init__.py
codefast/patterns/factory_method.py
codefast/patterns/observer.py
codefast/patterns/pipeline.py
codefast/patterns/pubsub.py
codefast/patterns/responsibility_chain.py
codefast/patterns/singleton.py
codefast/supercell/__init__.py
codefast/types/__init__.py
codefast-2024.11.13.dist-info/LICENSE
codefast-2024.11.13.dist-info/METADATA
codefast-2024.11.13.dist-info/WHEEL
codefast-2024.11.13.dist-info/top_level.txt
codefast-2024.11.13.dist-info/RECORD
